transcrypto/__init__.py
transcrypto/cli/__init__.py
transcrypto/cli/aeshash.py
transcrypto/cli/bidsecret.py
transcrypto/cli/clibase.py
transcrypto/cli/intmath.py
transcrypto/cli/publicalgos.py
transcrypto/core/__init__.py
transcrypto/core/aes.py
transcrypto/core/bid.py
transcrypto/core/constants.py
transcrypto/core/dsa.py
transcrypto/core/elgamal.py
transcrypto/core/hashes.py
transcrypto/core/key.py
transcrypto/core/modmath.py
transcrypto/core/rsa.py
transcrypto/core/sss.py
transcrypto/profiler.py
transcrypto/py.typed
transcrypto/transcrypto.py
transcrypto/utils/__init__.py
transcrypto/utils/base.py
transcrypto/utils/human.py
transcrypto/utils/logging.py
transcrypto/utils/saferandom.py
transcrypto/utils/stats.py
transcrypto/utils/timer.py
transcrypto-2.0.0.dist-info/METADATA
transcrypto-2.0.0.dist-info/WHEEL
transcrypto-2.0.0.dist-info/entry_points.txt
transcrypto-2.0.0.dist-info/licenses/LICENSE
transcrypto-2.0.0.dist-info/RECORD
