Metadata-Version: 2.4
Name: transcrypto
Version: 2.0.0
Summary: Basic crypto primitives, not intended for actual use, but as a companion to --Criptografia, Métodos e Algoritmos--
License-Expression: Apache-2.0
License-File: LICENSE
Keywords: cryptography,validation,encryption,signing,random-generation,prime-numbers,aes-encryption,decryption,rsa-cryptography,elgamal-encryption,dsa-algorithm,modular-mathematics,rsa,dsa,elgamal,aes,python,poetry,typer,rich,cli
Author: Daniel Balparda
Author-email: balparda@github.com
Requires-Python: >=3.12
Classifier: Programming Language :: Python :: 3
Classifier: Programming Language :: Python :: 3.12
Classifier: Programming Language :: Python :: 3.13
Classifier: Programming Language :: Python :: 3.14
Classifier: Operating System :: OS Independent
Classifier: Topic :: Utilities
Classifier: Topic :: Security :: Cryptography
Requires-Dist: cryptography (>=46.0)
Requires-Dist: gmpy2 (>=2.2)
Requires-Dist: platformdirs (>=4.5)
Requires-Dist: rich (>=14.3)
Requires-Dist: typer (>=0.21)
Requires-Dist: zstandard (>=0.25)
Project-URL: Changelog, https://github.com/balparda/transcrypto/blob/main/CHANGELOG.md
Project-URL: Homepage, https://github.com/balparda/transcrypto
Project-URL: Issues, https://github.com/balparda/transcrypto/issues
Project-URL: PyPI, https://pypi.org/project/transcrypto/
Project-URL: Repository, https://github.com/balparda/transcrypto
